Predviz/Predviz.py
Predviz/__init__.py
Predviz-0.0.4.dist-info/LICENSE.txt
Predviz-0.0.4.dist-info/METADATA
Predviz-0.0.4.dist-info/WHEEL
Predviz-0.0.4.dist-info/dependency_links.txt
Predviz-0.0.4.dist-info/top_level.txt
Predviz-0.0.4.dist-info/RECORD
