Metadata-Version: 2.1
Name: Predviz
Version: 0.0.4
Summary: Visualize the comparison between the Predicted or Forecasted Values generated by any Time-Series Forecasting Models and the Actual Values
Home-page: https://pypi.org/project/Predviz/
Author: Alfrethanov Christian Wijaya
Author-email: Alfrethanov Christian Wijaya <alfrethanovcwjy@gmail.com>
Project-URL: Repository, https://github.com/Arckitechttt/Predviz/tree/main
Project-URL: Author's Linkedin, https://www.linkedin.com/in/alfrethanovchristianwijaya/
Keywords: viz,visualizer,vis,time series,time-series,forecast,predict,preds,compare,comparison,Predviz,predviz,matplotlib,pandas
Classifier: Development Status :: 4 - Beta
Classifier: Programming Language :: Python :: 3
Classifier: License :: OSI Approved :: MIT License
Classifier: Operating System :: OS Independent
Requires-Python: >=3.8
License-File: LICENSE.txt
Requires-Dist: matplotlib >3.6
Requires-Dist: pandas >2.1
Requires-Dist: numpy >1.2
